cameralyze/__init__.py
cameralyze/model.py
cameralyze-1.4.8.dist-info/METADATA
cameralyze-1.4.8.dist-info/WHEEL
cameralyze-1.4.8.dist-info/top_level.txt
cameralyze-1.4.8.dist-info/RECORD
