Metadata-Version: 2.1
Name: cameralyze
Version: 1.4.8
Summary: Cameralyze No-Code AI Platform
Author: Cameralyze Inc
Author-email: info@cameralyze.com
License: UNKNOWN
Keywords: Cameralyze,AI,Computer Vision,NLP
Platform: UNKNOWN
Requires-Dist: requests (==2.28.2)
Requires-Dist: filetype (==1.2.0)
